durhamspintronics/__init__.py
durhamspintronics/general.py
durhamspintronics/analysis/__init__.py
durhamspintronics/analysis/microscope.py
durhamspintronics/analysis/moke.py
durhamspintronics/dataloaders/__init__.py
durhamspintronics/dataloaders/deposition.py
durhamspintronics/dataloaders/xray.py
durhamspintronics/experiments/__init__.py
durhamspintronics/experiments/fmr_vna.py
durhamspintronics/experiments/sotmoke.py
durhamspintronics/instruments/__init__.py
durhamspintronics/instruments/kepco.py
durhamspintronics/instruments/newport.py
durhamspintronics/instruments/ni.py
durhamspintronics/instruments/rohdeandschwarz.py
durhamspintronics-0.0.10.dist-info/LICENSE
durhamspintronics-0.0.10.dist-info/METADATA
durhamspintronics-0.0.10.dist-info/WHEEL
durhamspintronics-0.0.10.dist-info/top_level.txt
durhamspintronics-0.0.10.dist-info/RECORD
