Metadata-Version: 2.1
Name: durhamspintronics
Version: 0.0.10
Summary: A collection of instrument control and analysis tools for the Spintronics group at Durham University.
Home-page: https://github.com/Ben-Nicholson/durhamspintronics
Author: Ben Nicholson
Author-email: ben.nicholson@durham.ac.uk
Requires-Python: >=3
License-File: LICENSE
Requires-Dist: matplotlib
Requires-Dist: scipy
Requires-Dist: numpy
Requires-Dist: nidaqmx
Requires-Dist: pyserial
Requires-Dist: opencv-python
Requires-Dist: pillow
